{
  "0": "잠실",
  "1": "파크리오",
  "2": "자이",
  "3": "래미안",
  "4": "아이파크",
  "5": "더샵",
  "6": "힐스테이트",
  "7": "이편한|e편한|e-편한",
  "8": "푸르지오",
  "9": "동궁리치웰",
  "10": "롯데캐슬",
  "11": "데시앙",
  "12": "우성",
  "13": "삼성",
  "14": "두산",
  "15": "현대",
  "16": "신동아",
  "17": "경남",
  "18": "쌍용",
  "19": "대림",
  "20": "양지",
  "21": "삼익",
  "22": "성원",
  "23": "others",
  "24": "코오롱",
  "25": "주공",
  "26": "한신",
  "27": "sk|SK|에스케이",
  "28": "대우",
  "29": "삼환",
  "30": "동성",
  "31": "벽산",
  "32": "엘지",
  "33": "그레이스",
  "34": "동원로얄듀크"
}